odoo/addons/event_project/README.rst
odoo/addons/event_project/__init__.py
odoo/addons/event_project/__manifest__.py
odoo/addons/event_project/i18n/es.po
odoo/addons/event_project/i18n/event_project.pot
odoo/addons/event_project/i18n/it.po
odoo/addons/event_project/i18n/sl.po
odoo/addons/event_project/models/__init__.py
odoo/addons/event_project/models/event_event.py
odoo/addons/event_project/models/project_project.py
odoo/addons/event_project/models/project_task.py
odoo/addons/event_project/readme/CONTRIBUTORS.md
odoo/addons/event_project/readme/DESCRIPTION.md
odoo/addons/event_project/readme/USAGE.md
odoo/addons/event_project/security/ir.model.access.csv
odoo/addons/event_project/static/description/icon.png
odoo/addons/event_project/static/description/index.html
odoo/addons/event_project/static/images/event_form_view.png
odoo/addons/event_project/tests/__init__.py
odoo/addons/event_project/tests/test_event_project.py
odoo/addons/event_project/views/event_event_view.xml
odoo/addons/event_project/views/project_project_view.xml
odoo/addons/event_project/views/project_task_view.xml
odoo_addon_event_project-17.0.1.0.0.2.dist-info/METADATA
odoo_addon_event_project-17.0.1.0.0.2.dist-info/WHEEL
odoo_addon_event_project-17.0.1.0.0.2.dist-info/top_level.txt
odoo_addon_event_project-17.0.1.0.0.2.dist-info/RECORD
